{"namedChunkGroups":{"polyfill":{"name":"polyfill","assets":[{"name":"webpack-runtime-131e7f62b8eb3d63086e.js","size":5240},{"name":"polyfill-9297e683e8587f367349.js","size":85308}],"filteredAssets":0,"assetsSize":90548,"filteredAuxiliaryAssets":2,"auxiliaryAssetsSize":228587},"app":{"name":"app","assets":[{"name":"webpack-runtime-131e7f62b8eb3d63086e.js","size":5240},{"name":"framework-e886f61ee3e03a6355e5.js","size":129941},{"name":"532a2f07-35785486aa2d5e966460.js","size":239077},{"name":"app-ddb94722f33468eb2358.js","size":224341}],"filteredAssets":0,"assetsSize":598599,"filteredAuxiliaryAssets":4,"auxiliaryAssetsSize":1805276},"component---src-pages-404-js":{"name":"component---src-pages-404-js","assets":[{"name":"styles.2c56f7c2082b87fd254a.css","size":25029},{"name":"commons-bb82c2740fb50932a777.js","size":184732},{"name":"component---src-pages-404-js-a1e311307953b8fd2000.js","size":485}],"filteredAssets":0,"assetsSize":210246,"filteredAuxiliaryAssets":8,"auxiliaryAssetsSize":1092137},"component---src-pages-blog-index-js":{"name":"component---src-pages-blog-index-js","assets":[{"name":"styles.2c56f7c2082b87fd254a.css","size":25029},{"name":"commons-bb82c2740fb50932a777.js","size":184732},{"name":"component---src-pages-blog-index-js-223dbde5c2ebaf6ca778.js","size":1570}],"filteredAssets":0,"assetsSize":211331,"filteredAuxiliaryAssets":8,"auxiliaryAssetsSize":1096084},"component---src-pages-index-js":{"name":"component---src-pages-index-js","assets":[{"name":"styles.2c56f7c2082b87fd254a.css","size":25029},{"name":"commons-bb82c2740fb50932a777.js","size":184732},{"name":"component---src-pages-index-js-83ece7c98e71d78ae504.js","size":3203}],"filteredAssets":0,"assetsSize":212964,"filteredAuxiliaryAssets":8,"auxiliaryAssetsSize":1096140},"component---src-pages-projects-js":{"name":"component---src-pages-projects-js","assets":[{"name":"styles.2c56f7c2082b87fd254a.css","size":25029},{"name":"commons-bb82c2740fb50932a777.js","size":184732},{"name":"component---src-pages-projects-js-2a5f6a715a52b30a7a6b.js","size":1205}],"filteredAssets":0,"assetsSize":210966,"filteredAuxiliaryAssets":8,"auxiliaryAssetsSize":1094925}},"assetsByChunkName":{"polyfill":["webpack-runtime-131e7f62b8eb3d63086e.js","polyfill-9297e683e8587f367349.js"],"app":["webpack-runtime-131e7f62b8eb3d63086e.js","framework-e886f61ee3e03a6355e5.js","532a2f07-35785486aa2d5e966460.js","app-ddb94722f33468eb2358.js"],"component---src-pages-404-js":["styles.2c56f7c2082b87fd254a.css","commons-bb82c2740fb50932a777.js","component---src-pages-404-js-a1e311307953b8fd2000.js"],"component---src-pages-blog-index-js":["styles.2c56f7c2082b87fd254a.css","commons-bb82c2740fb50932a777.js","component---src-pages-blog-index-js-223dbde5c2ebaf6ca778.js"],"component---src-pages-index-js":["styles.2c56f7c2082b87fd254a.css","commons-bb82c2740fb50932a777.js","component---src-pages-index-js-83ece7c98e71d78ae504.js"],"component---src-pages-projects-js":["styles.2c56f7c2082b87fd254a.css","commons-bb82c2740fb50932a777.js","component---src-pages-projects-js-2a5f6a715a52b30a7a6b.js"]},"childAssetsByChunkName":{}}